comments_spamfighter
