Metadata-Version: 1.0
Name: django-comments-spamfighter
Version: 0.4
Summary: A Django app that contributes Akismet and Keyword blocking to your django comments.
Home-page: http://bitbucket.org/barttc/django-comments-spamfighter/
Author: Martin Mahner
Author-email: martin@mahner.org
License: BSD
Download-URL: http://bitbucket.org/barttc/django-comments-spamfighter/downloads/
Platform: UNKNOWN
Classifier: Development Status :: 3 - Alpha
Classifier: Environment :: Web Environment
Classifier: Intended Audience :: Developers
Classifier: License :: OSI Approved :: BSD License
Classifier: Operating System :: OS Independent
Classifier: Programming Language :: Python
Classifier: Framework :: Django
